almos/__init__.py
almos/__main__.py
almos/al_bayes.py
almos/almos.py
almos/argument_parser.py
almos/cluster.py
almos/el.py
almos/el_utils.py
almos/utils.py
almos/icons/almos_icon.png
almos/icons/almos_logo.png
almos/icons/almos_logo_old.png
almos/icons/overview_almos.jpg
almos_kit-1.0.0.dist-info/licenses/LICENSE
edbo/__init__.py
edbo/acquisition.py
edbo/model.py
edbo/optimizer.py
edbo/optimizer_botorch.py
edbo/scope_generator.py
edbo/utils.py
edbo/benchmark/__init__.py
edbo/benchmark/multiobjective_benchmark.py
almos_kit-1.0.0.dist-info/METADATA
almos_kit-1.0.0.dist-info/WHEEL
almos_kit-1.0.0.dist-info/top_level.txt
almos_kit-1.0.0.dist-info/RECORD
